nonebot_plugin_moyu/__init__.py
nonebot_plugin_moyu-0.3.4.dist-info/WHEEL
nonebot_plugin_moyu-0.3.4.dist-info/METADATA
nonebot_plugin_moyu-0.3.4.dist-info/licenses/LICENSE
nonebot_plugin_moyu-0.3.4.dist-info/RECORD
