Metadata-Version: 2.1
Name: nonebot-plugin-moyu
Version: 0.3.4
Summary: View your moyu calendar in NoneBot2
License: MIT
Author-email: Akirami <Akiramiaya@outlook.com>
Requires-Python: >=3.8
Requires-Dist: httpx[http2]>=0.23.0
Requires-Dist: nonebot-adapter-onebot>=2.0.0b1
Requires-Dist: nonebot-plugin-apscheduler>=0.1.2
Requires-Dist: nonebot2>=2.0.0b2
Project-URL: Homepage, https://github.com/A-kirami/nonebot-plugin-moyu
Project-URL: Repository, https://github.com/A-kirami/nonebot-plugin-moyu
